MANIFEST.in
README.rst
requirements-dev.txt
requirements.txt
setup.py
facebook/__init__.py
facebook/graphapi.py
tornado_facebook_sdk.egg-info/PKG-INFO
tornado_facebook_sdk.egg-info/SOURCES.txt
tornado_facebook_sdk.egg-info/dependency_links.txt
tornado_facebook_sdk.egg-info/requires.txt
tornado_facebook_sdk.egg-info/top_level.txt