Metadata-Version: 1.0
Name: tornado-facebook-sdk
Version: 0.1.0
Summary: A tornado based facebook graph api wrapper
Home-page: https://github.com/pauloalem/tornado-facebook-sdk
Author: Paulo Alem
Author-email: biggahed@gmail.com
License: OSI
Platform: UNKNOWN
